newrelic_extension_aredis/__init__.py
newrelic_extension_aredis/datastore_aredis.py
newrelic_extension_aredis-0.2.dist-info/LICENSE
newrelic_extension_aredis-0.2.dist-info/METADATA
newrelic_extension_aredis-0.2.dist-info/WHEEL
newrelic_extension_aredis-0.2.dist-info/entry_points.txt
newrelic_extension_aredis-0.2.dist-info/top_level.txt
newrelic_extension_aredis-0.2.dist-info/RECORD
