Metadata-Version: 2.1
Name: newrelic-extension-aredis
Version: 0.2
Summary: UNKNOWN
Home-page: UNKNOWN
License: Apache-2.0
Platform: UNKNOWN
Classifier: License :: OSI Approved :: Apache Software License
Requires-Dist: newrelic
Requires-Dist: aredis
